grablinkgooglesearch/__init__.py
grablinkgooglesearch/grablinkgooglesearch.py
grablinkgooglesearch-0.0.1.dist-info/LICENSE
grablinkgooglesearch-0.0.1.dist-info/METADATA
grablinkgooglesearch-0.0.1.dist-info/WHEEL
grablinkgooglesearch-0.0.1.dist-info/top_level.txt
grablinkgooglesearch-0.0.1.dist-info/RECORD
