Metadata-Version: 2.1
Name: grablinkgooglesearch
Version: 0.0.1
Summary: A python package for Grab Link Google Search and export it to a file csv or txt.
Home-page: https://github.com/H4rfu1/grablinkgooglesearch
Author: Moh Fahrul Hafidh
Author-email: admin@kulitekno.com
License: UNKNOWN
Platform: UNKNOWN
Classifier: Programming Language :: Python :: 3
Classifier: Operating System :: OS Independent
Classifier: License :: OSI Approved :: MIT License
License-File: LICENSE
